zope.intid-5.0-py3.9-nspkg.pth
zope/intid/__init__.py
zope/intid/configure.zcml
zope/intid/interfaces.py
zope/intid/subscribers.zcml
zope/intid/tests.py
zope.intid-5.0.dist-info/LICENSE.txt
zope.intid-5.0.dist-info/METADATA
zope.intid-5.0.dist-info/WHEEL
zope.intid-5.0.dist-info/namespace_packages.txt
zope.intid-5.0.dist-info/top_level.txt
zope.intid-5.0.dist-info/RECORD
